{"version":"sitegraph-local-light-impact-v2","tokenizer":"nfkc-lower-cjk-ngram-code","field_codes":{"title":"t","section":"s","nav_path":"n","attachment":"a","external":"e","system":"y","tag":"g"},"field_impacts":{"t":120,"s":60,"n":55,"a":95,"e":95,"y":95,"g":45},"block_size":32,"scoring_model":"impact-ordered-block-max-bm25f-lite-v2","entry_fields":["title","section","nav_path","tag","attachment","external","system"],"scope":{"index_id":"xsc__policy__2023","source_id":"xsc","facet":"policy","year":"2023","shard_ids":["xsc__policy__detail__2023__首页__b0","xsc__policy__detail__2023__首页__b1","xsc__policy__detail__2023__首页__b2","xsc__policy__detail__2023__首页__b3"]},"documents":[{"source_id":"xsc","source":"学生工作部（处）","academic_year":null,"attachment_count":0,"date_kind":"published","source_domain":"xsc.njupt.edu.cn","canonical_title":"第五届优秀学子宣讲团走进集成电路科学与工程学院（产教融合学院）","updated_at":null,"nav_path_text":"首页 / 思政专题","record_type":"detail","section_id":"xsc_home_link_8c1ecf533e23","doc_index":7987,"task_kind":"student_affairs","collection_method":"search_record","term":null,"title":"第五届优秀学子宣讲团走进集成电路科学与工程学院（产教融合学院）","published_at":"2023-06-02","facet":"policy","dedupe_key":"xsc:detail:02f9300805daf720","authority_profile":"xsc_student_affairs","recorded_at":null,"version_date":null,"date_confidence":"source_published","id":"xsc-detail-5f494eb16a26a3ddf2b5","section":"思政专题","nav_path":["首页","思政专题"],"shard":{"shard_id":"xsc__policy__detail__2023__首页__b0","path":"generated/collections/njupt-public/sitegraph/full_shards/full.xsc__policy__detail__2023__首页__b0.502f057bdce5f9a4.json"},"url":"https://xsc.njupt.edu.cn/2023/0621/c1151a244316/page.htm"},{"source_id":"xsc","source":"学生工作部（处）","academic_year":null,"attachment_count":0,"date_kind":"published","source_domain":"xsc.njupt.edu.cn","canonical_title":"我校开展2023年度新入职辅导员培训","updated_at":null,"nav_path_text":"首页 / 辅导员队伍建设","record_type":"detail","section_id":"xsc_home_link_d05189e866fc","doc_index":8064,"task_kind":"student_affairs","collection_method":"search_record","term":null,"title":"我校开展2023年度新入职辅导员培训","published_at":"2023-05-16","facet":"policy","dedupe_key":"xsc:detail:ae5345c78547fed2","authority_profile":"xsc_student_affairs","recorded_at":null,"version_date":null,"date_confidence":"source_published","id":"xsc-detail-7b8cc4dba8c8c287bad3","section":"辅导员队伍建设","nav_path":["首页","辅导员队伍建设"],"shard":{"shard_id":"xsc__policy__detail__2023__首页__b1","path":"generated/collections/njupt-public/sitegraph/full_shards/full.xsc__policy__detail__2023__首页__b1.0744cfa85c93ac3a.json"},"url":"https://xsc.njupt.edu.cn/2023/0516/c1152a241036/page.htm"},{"source_id":"xsc","source":"学生工作部（处）","academic_year":null,"attachment_count":0,"date_kind":"published","source_domain":"xsc.njupt.edu.cn","canonical_title":"我校举办《辅导员思享汇》第一季第七场活动","updated_at":null,"nav_path_text":"首页 / 辅导员队伍建设","record_type":"detail","section_id":"xsc_home_link_d05189e866fc","doc_index":8066,"task_kind":"student_affairs","collection_method":"search_record","term":null,"title":"我校举办《辅导员思享汇》第一季第七场活动","published_at":"2023-04-15","facet":"policy","dedupe_key":"xsc:detail:2865cfb073b6f6b4","authority_profile":"xsc_student_affairs","recorded_at":null,"version_date":null,"date_confidence":"source_published","id":"xsc-detail-28fa70f38bbe6971962f","section":"辅导员队伍建设","nav_path":["首页","辅导员队伍建设"],"shard":{"shard_id":"xsc__policy__detail__2023__首页__b1","path":"generated/collections/njupt-public/sitegraph/full_shards/full.xsc__policy__detail__2023__首页__b1.0744cfa85c93ac3a.json"},"url":"https://xsc.njupt.edu.cn/2023/0417/c1152a238952/page.htm"},{"source_id":"xsc","source":"学生工作部（处）","academic_year":null,"attachment_count":0,"date_kind":"published_and_version","source_domain":"xsc.njupt.edu.cn","canonical_title":"青春不停步，永远跟党走 ——贝尔英才学院学生党支部举行发展对象答辩","updated_at":null,"nav_path_text":"首页 / 学院风采","record_type":"detail","section_id":"xsc_home_module_6c9d38d56d8b","doc_index":8796,"task_kind":"student_affairs","collection_method":"search_record","term":null,"title":"青春不停步，永远跟党走 ——贝尔英才学院学生党支部举行发展对象答辩","published_at":"2023-11-14","facet":"policy","dedupe_key":"xsc:detail:b613a676821bf036","authority_profile":"xsc_student_affairs","recorded_at":null,"version_date":"2023-10-25","date_confidence":"source_published_and_title_version","id":"xsc-detail-cebcd32686ceb65f1df0","section":"学院风采","nav_path":["首页","学院风采"],"shard":{"shard_id":"xsc__policy__detail__2023__首页__b3","path":"generated/collections/njupt-public/sitegraph/full_shards/full.xsc__policy__detail__2023__首页__b3.a539730e25e45769.json"},"url":"https://xsc.njupt.edu.cn/2023/1031/c1175a248775/page.htm"},{"source_id":"xsc","source":"学生工作部（处）","academic_year":null,"attachment_count":0,"date_kind":"published","source_domain":"xsc.njupt.edu.cn","canonical_title":"考研启航，放飞梦想 ——教育科学与技术学院2021级年级大会","updated_at":null,"nav_path_text":"首页 / 学院风采","record_type":"detail","section_id":"xsc_home_module_6c9d38d56d8b","doc_index":8807,"task_kind":"student_affairs","collection_method":"search_record","term":null,"title":"考研启航，放飞梦想 ——教育科学与技术学院2021级年级大会","published_at":"2023-11-02","facet":"policy","dedupe_key":"xsc:detail:02b6d486440ed35b","authority_profile":"xsc_student_affairs","recorded_at":null,"version_date":null,"date_confidence":"source_published","id":"xsc-detail-9495500bdd726289012c","section":"学院风采","nav_path":["首页","学院风采"],"shard":{"shard_id":"xsc__policy__detail__2023__首页__b2","path":"generated/collections/njupt-public/sitegraph/full_shards/full.xsc__policy__detail__2023__首页__b2.676f00ef4ed3dde9.json"},"url":"https://xsc.njupt.edu.cn/2023/1211/c1175a252126/page.htm"},{"source_id":"xsc","source":"学生工作部（处）","academic_year":null,"attachment_count":0,"date_kind":"published","source_domain":"xsc.njupt.edu.cn","canonical_title":"第五届优秀学子宣讲团走进集成电路科学与工程学院（产教融合学院）","updated_at":null,"nav_path_text":"首页 / 学院风采","record_type":"detail","section_id":"xsc_home_module_6c9d38d56d8b","doc_index":8889,"task_kind":"student_affairs","collection_method":"search_record","term":null,"title":"第五届优秀学子宣讲团走进集成电路科学与工程学院（产教融合学院）","published_at":"2023-06-02","facet":"policy","dedupe_key":"xsc:detail:02f9300805daf720","authority_profile":"xsc_student_affairs","recorded_at":null,"version_date":null,"date_confidence":"source_published","id":"xsc-detail-e03b058f8d097e74ecad","section":"学院风采","nav_path":["首页","学院风采"],"shard":{"shard_id":"xsc__policy__detail__2023__首页__b2","path":"generated/collections/njupt-public/sitegraph/full_shards/full.xsc__policy__detail__2023__首页__b2.676f00ef4ed3dde9.json"},"url":"https://xsc.njupt.edu.cn/2023/0621/c1175a244316/page.htm"},{"source_id":"xsc","source":"学生工作部（处）","academic_year":null,"attachment_count":0,"date_kind":"published","source_domain":"xsc.njupt.edu.cn","canonical_title":"电光柔院2022级光电信息科学与工程专业开展“五一假期安全教育”主题班会","updated_at":null,"nav_path_text":"首页 / 学院风采","record_type":"detail","section_id":"xsc_home_module_6c9d38d56d8b","doc_index":8916,"task_kind":"student_affairs","collection_method":"search_record","term":null,"title":"电光柔院2022级光电信息科学与工程专业开展“五一假期安全教育”主题班会","published_at":"2023-04-28","facet":"policy","dedupe_key":"xsc:detail:7f8f35633a935729","authority_profile":"xsc_student_affairs","recorded_at":null,"version_date":null,"date_confidence":"source_published","id":"xsc-detail-d7b991d1122a17247732","section":"学院风采","nav_path":["首页","学院风采"],"shard":{"shard_id":"xsc__policy__detail__2023__首页__b0","path":"generated/collections/njupt-public/sitegraph/full_shards/full.xsc__policy__detail__2023__首页__b0.502f057bdce5f9a4.json"},"url":"https://xsc.njupt.edu.cn/2023/0506/c1175a240422/page.htm"},{"source_id":"xsc","source":"学生工作部（处）","academic_year":null,"attachment_count":0,"date_kind":"published_and_version","source_domain":"xsc.njupt.edu.cn","canonical_title":"“严格日常管理规范，共筑五一安全屏障”——教育科学与技术学院召开2021级年级大会","updated_at":null,"nav_path_text":"首页 / 学院风采","record_type":"detail","section_id":"xsc_home_module_6c9d38d56d8b","doc_index":8917,"task_kind":"student_affairs","collection_method":"search_record","term":null,"title":"“严格日常管理规范，共筑五一安全屏障”——教育科学与技术学院召开2021级年级大会","published_at":"2023-04-28","facet":"policy","dedupe_key":"xsc:detail:c7f1319087a9a870","authority_profile":"xsc_student_affairs","recorded_at":null,"version_date":"2023-04-26","date_confidence":"source_published_and_title_version","id":"xsc-detail-cd5c0f5830e22b74e22e","section":"学院风采","nav_path":["首页","学院风采"],"shard":{"shard_id":"xsc__policy__detail__2023__首页__b0","path":"generated/collections/njupt-public/sitegraph/full_shards/full.xsc__policy__detail__2023__首页__b0.502f057bdce5f9a4.json"},"url":"https://xsc.njupt.edu.cn/2023/0427/c1175a239996/page.htm"},{"source_id":"xsc","source":"学生工作部（处）","academic_year":null,"attachment_count":0,"date_kind":"published","source_domain":"xsc.njupt.edu.cn","canonical_title":"电光柔院2021级成功开展“立鸿鹄志，做奋斗者”主题学风建设月专题活动","updated_at":null,"nav_path_text":"首页 / 学院风采","record_type":"detail","section_id":"xsc_home_module_6c9d38d56d8b","doc_index":8936,"task_kind":"student_affairs","collection_method":"search_record","term":null,"title":"电光柔院2021级成功开展“立鸿鹄志，做奋斗者”主题学风建设月专题活动","published_at":"2023-04-03","facet":"policy","dedupe_key":"xsc:detail:9ac612b1c5de21af","authority_profile":"xsc_student_affairs","recorded_at":null,"version_date":null,"date_confidence":"source_published","id":"xsc-detail-cd01471e89c0707f0921","section":"学院风采","nav_path":["首页","学院风采"],"shard":{"shard_id":"xsc__policy__detail__2023__首页__b0","path":"generated/collections/njupt-public/sitegraph/full_shards/full.xsc__policy__detail__2023__首页__b0.502f057bdce5f9a4.json"},"url":"https://xsc.njupt.edu.cn/2023/0423/c1175a239546/page.htm"},{"source_id":"xsc","source":"学生工作部（处）","academic_year":null,"attachment_count":0,"date_kind":"published","source_domain":"xsc.njupt.edu.cn","canonical_title":"文明始于心，洁净践于行——电光柔学院2020级电科专业开展春季学生宿舍安全卫生检查活动","updated_at":null,"nav_path_text":"首页 / 学院风采","record_type":"detail","section_id":"xsc_home_module_6c9d38d56d8b","doc_index":8950,"task_kind":"student_affairs","collection_method":"search_record","term":null,"title":"文明始于心，洁净践于行——电光柔学院2020级电科专业开展春季学生宿舍安全卫生检查活动","published_at":"2023-03-24","facet":"policy","dedupe_key":"xsc:detail:6808ad3e3d6df46a","authority_profile":"xsc_student_affairs","recorded_at":null,"version_date":null,"date_confidence":"source_published","id":"xsc-detail-3291a0413f22ca9eb78a","section":"学院风采","nav_path":["首页","学院风采"],"shard":{"shard_id":"xsc__policy__detail__2023__首页__b1","path":"generated/collections/njupt-public/sitegraph/full_shards/full.xsc__policy__detail__2023__首页__b1.0744cfa85c93ac3a.json"},"url":"https://xsc.njupt.edu.cn/2023/0317/c1175a235659/page.htm"}]}