{"version":"sitegraph-local-light-impact-v2","tokenizer":"nfkc-lower-cjk-ngram-code","field_codes":{"title":"t","section":"s","nav_path":"n","attachment":"a","external":"e","system":"y","tag":"g"},"field_impacts":{"t":120,"s":60,"n":55,"a":95,"e":95,"y":95,"g":45},"block_size":32,"scoring_model":"impact-ordered-block-max-bm25f-lite-v2","entry_fields":["title","section","nav_path","tag","attachment","external","system"],"scope":{"index_id":"jwc__external__2000","source_id":"jwc","facet":"external","year":"2000","shard_ids":["jwc__external__external__2000__首页__b2"]},"documents":[{"canonical_title":"中华人民共和国国家通用语言文字法 2000-10-31","source_id":"jwc","id":"jwc-external-0729b0b9bb87c40d222b","updated_at":null,"version_date":"2000-10-31","title":"中华人民共和国国家通用语言文字法 2000-10-31","date_kind":"version","date_confidence":"title_or_attachment","nav_path_text":"首页 / 法律","academic_year":null,"term":null,"shard":{"shard_id":"jwc__external__external__2000__首页__b2","path":"generated/collections/njupt-public/sitegraph/full_shards/full.jwc__external__external__2000__首页__b2.9898deedc1517a87.json"},"source_domain":"jwc.njupt.edu.cn","section_id":"jwc_home_link_311e2a333158","section":"法律","nav_path":["首页","法律"],"url":"http://www.moe.gov.cn/jyb_sjzl/sjzl_zcfg/zcfg_jyfl/202204/t20220421_620290.html","doc_index":7889,"recorded_at":"2026-05-28T14:45:39.920098+00:00","record_type":"external","published_at":null,"facet":"external","source":"本科生院 / 教务处","dedupe_key":"jwc:external:3ec810dc09c6c581","collection_method":"external_record_only","attachment_count":0,"authority_profile":"jwc_academic","task_kind":"broad_exploratory"}]}