{"version":"sitegraph-local-light-impact-v2","tokenizer":"nfkc-lower-cjk-ngram-code","field_codes":{"title":"t","section":"s","nav_path":"n","attachment":"a","external":"e","system":"y","tag":"g"},"field_impacts":{"t":120,"s":60,"n":55,"a":95,"e":95,"y":95,"g":45},"block_size":32,"scoring_model":"impact-ordered-block-max-bm25f-lite-v2","entry_fields":["title","section","nav_path","tag","attachment","external","system"],"scope":{"index_id":"xsc__news__2026","source_id":"xsc","facet":"news","year":"2026","shard_ids":["xsc__news__detail__2026__首页__b1"]},"documents":[{"doc_index":8109,"shard":{"shard_id":"xsc__news__detail__2026__首页__b1","path":"generated/collections/njupt-public/sitegraph/full_shards/full.xsc__news__detail__2026__首页__b1.71dc4eaced70c9b5.json"},"date_kind":"published","record_type":"detail","canonical_title":"学生处党支部与32238部队82分队党支部开展党建联建活动","section_id":"xsc_home_link_c6623c687641","version_date":null,"section":"支部动态","attachment_count":0,"task_kind":"student_affairs","term":null,"authority_profile":"xsc_student_affairs","dedupe_key":"xsc:detail:de2862a98b3ad77a","url":"https://xsc.njupt.edu.cn/2026/0330/c16750a298759/page.htm","academic_year":null,"source":"学生工作部（处）","date_confidence":"source_published","source_id":"xsc","facet":"news","id":"xsc-detail-90d23ef8020d9a81a439","updated_at":null,"title":"学生处党支部与32238部队82分队党支部开展党建联建活动","published_at":"2026-03-30","nav_path_text":"首页 / 支部动态","recorded_at":null,"source_domain":"xsc.njupt.edu.cn","nav_path":["首页","支部动态"],"collection_method":"search_record"}]}