{"version":"sitegraph-local-light-impact-v2","tokenizer":"nfkc-lower-cjk-ngram-code","field_codes":{"title":"t","section":"s","nav_path":"n","attachment":"a","external":"e","system":"y","tag":"g"},"field_impacts":{"t":120,"s":60,"n":55,"a":95,"e":95,"y":95,"g":45},"block_size":32,"scoring_model":"impact-ordered-block-max-bm25f-lite-v2","entry_fields":["title","section","nav_path","tag","attachment","external","system"],"scope":{"index_id":"cxcy__policy__2018","source_id":"cxcy","facet":"policy","year":"2018","shard_ids":["cxcy__policy__detail__2018__首页__b1"]},"documents":[{"doc_index":10141,"shard":{"shard_id":"cxcy__policy__detail__2018__首页__b1","path":"generated/collections/njupt-public/sitegraph/full_shards/full.cxcy__policy__detail__2018__首页__b1.1221624f98deaf4a.json"},"date_kind":"published","record_type":"detail","canonical_title":"关于举办第十届中国大学生服务外包创新创业大赛南京邮电大学校级选拔赛的通知","section_id":"cxcy_home_module_b3b0e005b420","version_date":null,"section":"通知公告","attachment_count":0,"task_kind":"innovation_entrepreneurship","term":null,"authority_profile":"cxcy_innovation","dedupe_key":"cxcy:detail:7f0fad27fd7f3b17","url":"https://cxcy.njupt.edu.cn/2022/0711/c11336a223942/page.htm","academic_year":null,"source":"创新创业教育学院","date_confidence":"source_published","source_id":"cxcy","facet":"policy","id":"cxcy-detail-cf94aacfc8a7bed6118b","updated_at":null,"title":"关于举办第十届中国大学生服务外包创新创业大赛南京邮电大学校级选拔赛的通知","published_at":"2018-11-09","nav_path_text":"首页 / 通知公告","recorded_at":null,"source_domain":"cxcy.njupt.edu.cn","nav_path":["首页","通知公告"],"collection_method":"search_record"},{"doc_index":10142,"shard":{"shard_id":"cxcy__policy__detail__2018__首页__b1","path":"generated/collections/njupt-public/sitegraph/full_shards/full.cxcy__policy__detail__2018__首页__b1.1221624f98deaf4a.json"},"date_kind":"published","record_type":"detail","canonical_title":"关于举办“扇贝杯”南京邮电大学第三届软件和信息技术专业人才大赛的通知","section_id":"cxcy_home_module_b3b0e005b420","version_date":null,"section":"通知公告","attachment_count":0,"task_kind":"innovation_entrepreneurship","term":null,"authority_profile":"cxcy_innovation","dedupe_key":"cxcy:detail:fff75514563725a0","url":"https://cxcy.njupt.edu.cn/2022/0711/c11336a223941/page.htm","academic_year":null,"source":"创新创业教育学院","date_confidence":"source_published","source_id":"cxcy","facet":"policy","id":"cxcy-detail-165874932e2c2ee43baa","updated_at":null,"title":"关于举办“扇贝杯”南京邮电大学第三届软件和信息技术专业人才大赛的通知","published_at":"2018-11-09","nav_path_text":"首页 / 通知公告","recorded_at":null,"source_domain":"cxcy.njupt.edu.cn","nav_path":["首页","通知公告"],"collection_method":"search_record"}]}