[{"doc_index":9815,"id":"cxcy-detail-bafcbeced369448338de","record_type":"detail","page_type":"detail_article_page","facet":"news","title":"我校荣获第九届中国国际“互联网+”大学生创新创业大赛江苏省决赛一等奖","url":"https://cxcy.njupt.edu.cn/2023/0906/c15469a246101/page.htm","source_id":"cxcy","source":"创新创业教育学院","source_domain":"cxcy.njupt.edu.cn","section_id":"cxcy_home_module_824f590b522f","section":"新闻资讯","nav_path":["首页","新闻资讯"],"nav_path_text":"首页 / 新闻资讯","canonical_title":"我校荣获第九届中国国际“互联网+”大学生创新创业大赛江苏省决赛一等奖","published_at":"2023-07-20","updated_at":null,"recorded_at":null,"version_date":null,"date_kind":"published","date_confidence":"source_published","academic_year":null,"term":null,"task_kind":"innovation_entrepreneurship","authority_profile":"cxcy_innovation","dedupe_key":"cxcy:detail:c39867c88ac0f810","publisher":null,"summary":"7 月 16-19 日，第九届中国国际“互联网 + ”大学生创新创业大赛江苏省决赛在南京举行，经过激烈争夺，我校共获得一等奖 10 项（主赛道 7 项、红旅 2 项、产业赛道 1 项）、二等奖 18 项、三等奖 4 项，一等奖获奖总数位居全省第四。我校同时获得“主赛道优秀组织奖”和“红旅优秀组织奖”，外国语学院的“深耕学堂 - 中国故事多语传播者”获得最佳公","attachment_count":0,"hash":"0cf08983b1c3fc7fd5d0","tags":["homepage_module","news","detail"],"collection_method":"search_record","provenance":{"site_id":"cxcy","section_id":"cxcy_home_module_824f590b522f","nav_path":["首页","新闻资讯"],"source_url":"https://cxcy.njupt.edu.cn/2023/0906/c15469a246101/page.htm","outcome":"search_record","external_category":null},"content":"7 月 16-19 日，第九届中国国际“互联网 + ”大学生创新创业大赛江苏省决赛在南京举行，经过激烈争夺，我校共获得一等奖 10 项（主赛道 7 项、红旅 2 项、产业赛道 1 项）、二等奖 18 项、三等奖 4 项，一等奖获奖总数位居全省第四。我校同时获得“主赛道优秀组织奖”和“红旅优秀组织奖”，外国语学院的“深耕学堂 - 中国故事多语传播者”获得最佳公益奖（江苏省唯一），获奖总数和等级实现突破。 学校一贯重视创新创业教育工作，由创新创业教育学院统筹协调，教务处、学生工作处、团委、对外联络处、科研院、研究生院等多部门通力合作，各学院认真组织广大师生积极参与。本次 “互联网 + ”校赛中，我校 1292 支团队报名、 4556 人次参赛，项目涉及新工科、新医科、新农科、新文科等多个领域。在此次省赛决赛中，我校参赛选手团结拼搏、勇于争先，展现了敢于创新、善于创新的青春风采，持续擦亮学校“无创新，不南邮”的创新名片。","attachments":[]}]