{"version":"sitegraph-local-body-index-routed-v1","tokenizer":"nfkc-lower-cjk-ngram-code","field_codes":{"summary":"m","content":"c"},"entry_fields":["summary","content"],"tokens":{"务院":{"m":[9582,9583],"c":[9582,9583]},"深化高等":{"m":[9582]},"学校创":{"m":[9582],"c":[9582,9583]},"国办":{"m":[9582],"c":[9582,9583]},"创业":{"m":[9582,9583,10147],"c":[9582,9583,10147]},"民政":{"m":[9582],"c":[9582]},"人民":{"m":[9582],"c":[9582]},"机构":{"m":[9582],"c":[9582]},"属机构":{"m":[9582],"c":[9582]},"各直属机":{"m":[9582]},"国务院各部委":{"m":[9582],"c":[9582]},"各部委":{"m":[9582],"c":[9582]},"各直属机构":{"m":[9582],"c":[9582]},"创新":{"m":[9582,9583,10147],"c":[9582,9583,10147]},"部委":{"m":[9582],"c":[9582]},"各省":{"m":[9582],"c":[9582]},"深化高等学校创新创业教育改革":{"m":[9582],"c":[9582]},"市人民":{"m":[9582],"c":[9582]},"创业教":{"m":[9582,10147],"c":[9582,9583,10147]},"创新创":{"m":[9582,10147],"c":[9582,9583,10147]},"36":{"m":[9582],"c":[9582,9583]},"国务":{"m":[9582,9583],"c":[9582,9583]},"教育":{"m":[9582,9583,10147],"c":[9582,9583,10147]},"号各省":{"m":[9582],"c":[9582]},"新创":{"m":[9582,9583,10147],"c":[9582,9583,10147]},"校创新":{"m":[9582],"c":[9582,9583,10147]},"高等学校":{"m":[9582]},"各直属":{"m":[9582],"c":[9582]},"国办发":{"m":[9582],"c":[9582,9583]},"自治区":{"m":[9582],"c":[9582]},"辖市":{"m":[9582],"c":[9582]},"改革":{"m":[9582,9583],"c":[9582,9583,10147]},"校创":{"m":[9582,9583],"c":[9582,9583,10147]},"2015":{"m":[9582],"c":[9582,9583]},"市人民政":{"m":[9582]},"人民政府":{"m":[9582]},"院各":{"m":[9582],"c":[9582]},"深化高":{"m":[9582],"c":[9582,9583]},"院各部":{"m":[9582],"c":[9582]},"业教育":{"m":[9582,10147],"c":[9582,9583,10147]},"直辖市人民政府":{"m":[9582],"c":[9582]},"市人":{"m":[9582],"c":[9582]},"化高":{"m":[9582,9583],"c":[9582,9583]},"直属机构":{"m":[9582]},"人民政":{"m":[9582],"c":[9582]},"教育改":{"m":[9582],"c":[9582,9583]},"辖市人民":{"m":[9582]},"化高等学":{"m":[9582]},"各部":{"m":[9582],"c":[9582]},"办发":{"m":[9582],"c":[9582,9583]},"等学":{"m":[9582,9583],"c":[9582,9583]},"高等学":{"m":[9582],"c":[9582,9583]},"号各":{"m":[9582],"c":[9582]},"直辖":{"m":[9582],"c":[9582]},"各直":{"m":[9582],"c":[9582]},"高等":{"m":[9582,9583],"c":[9582,9583,10147]},"国务院各":{"m":[9582]},"直辖市":{"m":[9582],"c":[9582]},"等学校创":{"m":[9582]},"学校":{"m":[9582,9583],"c":[9582,9583]},"育改":{"m":[9582],"c":[9582,9583]},"院各部委":{"m":[9582]},"业教":{"m":[9582,10147],"c":[9582,9583,10147]},"务院各部":{"m":[9582]},"直属":{"m":[9582],"c":[9582]},"等学校":{"m":[9582],"c":[9582,9583]},"务院各":{"m":[9582],"c":[9582]},"深化":{"m":[9582,9583,10147],"c":[9582,9583,10147]},"新创业":{"m":[9582,10147],"c":[9582,9583,10147]},"自治":{"m":[9582],"c":[9582]},"民政府":{"m":[9582],"c":[9582]},"属机":{"m":[9582],"c":[9582]},"直属机":{"m":[9582],"c":[9582]},"国务院":{"m":[9582],"c":[9582,9583]},"化高等":{"m":[9582],"c":[9582,9583]},"辖市人":{"m":[9582],"c":[9582]},"直辖市人":{"m":[9582]},"政府":{"m":[9582],"c":[9582]},"育改革":{"m":[9582],"c":[9582,9583]},"治区":{"m":[9582],"c":[9582]},"培养":{"c":[9582,9583,10147],"m":[9583,10147]},"要举":{"c":[9582]},"是国家":{"c":[9582]},"质量创":{"c":[9582]},"教育综":{"c":[9582]},"高质量":{"c":[9582]},"动发":{"c":[9582,9583]},"济提":{"c":[9582]},"就业的":{"c":[9582]},"更高":{"c":[9582]},"推进高":{"c":[9582]},"重要举":{"c":[9582]},"业的":{"c":[9582]},"国家实":{"c":[9582]},"促进经":{"c":[9582]},"增效":{"c":[9582]},"毕业生":{"c":[9582]},"八大":{"c":[9582]},"济提质":{"c":[9582]},"创新驱":{"c":[9582]},"的十":{"c":[9582]},"的重要":{"c":[9582]},"大对":{"c":[9582]},"十八":{"c":[9582]},"是推进":{"c":[9582]},"促进经济提质增效升级的迫切需要":{"c":[9582]},"养作":{"c":[9582]},"高质":{"c":[9582]},"育综合":{"c":[9582]},"切需":{"c":[9582]},"是推":{"c":[9582]},"动发展":{"c":[9582]},"量创业":{"c":[9582]},"进经济":{"c":[9582]},"质增效":{"c":[9582]},"举措":{"c":[9582]},"业就业":{"c":[9582]},"实施":{"c":[9582,9583]},"级的迫":{"c":[9582]},"切需要":{"c":[9582]},"才培":{"c":[9582,9583,10147],"m":[9583,10147]},"高校":{"c":[9582,9583]},"战略":{"c":[9582,9583]},"校毕":{"c":[9582]},"迫切需":{"c":[9582]},"毕业":{"c":[9582]},"增效升":{"c":[9582]},"家实施":{"c":[9582]},"进高校":{"c":[9582]},"的迫":{"c":[9582]},"促进":{"c":[9582]},"人才":{"c":[9582,9583,10147],"m":[9583,10147]},"生更高":{"c":[9582]},"业的重":{"c":[9582]},"进高":{"c":[9582]},"党的":{"c":[9582]},"新驱":{"c":[9582,9583]},"驱动":{"c":[9582,9583]},"校毕业":{"c":[9582]},"要举措":{"c":[9582]},"业人":{"c":[9582]},"更高质":{"c":[9582]},"生更":{"c":[9582]},"就业":{"c":[9582]},"合改":{"c":[9582]},"施创":{"c":[9582]},"效升":{"c":[9582]},"新驱动":{"c":[9582]},"经济":{"c":[9582]},"实施创":{"c":[9582]},"施创新":{"c":[9582]},"质增":{"c":[9582]},"是国家实施创新驱动发展战略":{"c":[9582]},"是推进高等教育综合改革":{"c":[9582]},"驱动发":{"c":[9582]},"提质":{"c":[9582]},"效升级":{"c":[9582]},"发展":{"c":[9582,9583,10147],"m":[10147]},"展战略":{"c":[9582]},"育综":{"c":[9582]},"综合改":{"c":[9582]},"等教育":{"c":[9582,9583],"m":[9583]},"促进高":{"c":[9582]},"对创":{"c":[9582]},"业生":{"c":[9582]},"的重":{"c":[9582]},"高校毕":{"c":[9582]},"的迫切":{"c":[9582]},"合改革":{"c":[9582]},"发展战":{"c":[9582]},"重要":{"c":[9582,9583]},"等教":{"c":[9582,9583],"m":[9583]},"是国":{"c":[9582]},"展战":{"c":[9582,9583]},"创业就":{"c":[9582]},"国家":{"c":[9582]},"提质增":{"c":[9582]},"迫切":{"c":[9582]},"升级":{"c":[9582]},"经济提":{"c":[9582]},"进经":{"c":[9582]},"进高等":{"c":[9582]},"家实":{"c":[9582]},"级的":{"c":[9582]},"质量":{"c":[9582,9583],"m":[9583]},"业就":{"c":[9582]},"业生更":{"c":[9582]},"需要":{"c":[9582]},"量创":{"c":[9582]},"升级的":{"c":[9582]},"推进":{"c":[9582]},"综合":{"c":[9582]},"高等教":{"c":[9582,9583],"m":[9583]},"提高高等":{"m":[9583]},"推动大众创业万众创新":{"m":[9583],"c":[9583]},"才培养":{"m":[9583,10147],"c":[9583,10147]},"为改革人":{"m":[9583]},"万众创":{"m":[9583],"c":[9583]},"众创业万":{"m":[9583]},"培养机制":{"m":[9583]},"业万众创":{"m":[9583]},"养机制":{"m":[9583],"c":[9583]},"众创":{"m":[9583],"c":[9583]},"大众创":{"m":[9583],"c":[9583]},"众创新":{"m":[9583],"c":[9583]},"育质":{"m":[9583],"c":[9583]},"创业万众":{"m":[9583]},"等教育质":{"m":[9583]},"教育质":{"m":[9583],"c":[9583]},"万众":{"m":[9583],"c":[9583]},"业万众":{"m":[9583],"c":[9583]},"培养机":{"m":[9583],"c":[9583]},"大众":{"m":[9583],"c":[9583]},"万众创新":{"m":[9583]},"推动大众":{"m":[9583]},"创业万":{"m":[9583],"c":[9583]},"于深":{"m":[9583],"c":[9583]},"教育质量":{"m":[9583]},"推动":{"m":[9583],"c":[9583,10147]},"提高高":{"m":[9583],"c":[9583]},"提高":{"m":[9583],"c":[9583]},"众创业":{"m":[9583],"c":[9583]},"高高":{"m":[9583],"c":[9583]},"提高高等教育质量":{"m":[9583],"c":[9583]},"人才培":{"m":[9583,10147],"c":[9583,10147]},"育质量":{"m":[9583],"c":[9583]},"为改革":{"m":[9583],"c":[9583]},"才培养机":{"m":[9583]},"改革人":{"m":[9583],"c":[9583]},"改革人才":{"m":[9583]},"院办":{"m":[9583],"c":[9583]},"革人才培":{"m":[9583]},"根据":{"m":[9583],"c":[9583]},"高高等":{"m":[9583],"c":[9583]},"革人":{"m":[9583],"c":[9583]},"动大":{"m":[9583],"c":[9583]},"大众创业":{"m":[9583]},"为改革人才培养机制":{"m":[9583],"c":[9583]},"关于":{"m":[9583],"c":[9583]},"动大众创":{"m":[9583]},"高高等教":{"m":[9583]},"公厅":{"m":[9583],"c":[9583]},"推动大":{"m":[9583],"c":[9583]},"为改":{"m":[9583],"c":[9583]},"高等教育":{"m":[9583]},"业万":{"m":[9583],"c":[9583]},"厅关":{"m":[9583],"c":[9583]},"革人才":{"m":[9583],"c":[9583]},"办公":{"m":[9583],"c":[9583]},"动大众":{"m":[9583],"c":[9583]},"养机":{"m":[9583],"c":[9583]},"人才培养":{"m":[9583,10147]},"机制":{"m":[9583],"c":[9583,10147]},"重要紧":{"c":[9583]},"为一":{"c":[9583]},"迫任务":{"c":[9583]},"与人":{"c":[9583]},"改革作":{"c":[9583]},"任务来":{"c":[9583]},"施科教":{"c":[9583]},"才强省":{"c":[9583]},"本实施":{"c":[9583]},"和创":{"c":[9583]},"合我":{"c":[9583]},"是实施":{"c":[9583]},"作为":{"c":[9583]},"任务":{"c":[9583]},"项重":{"c":[9583]},"一项重":{"c":[9583]},"强省":{"c":[9583]},"我省实":{"c":[9583]},"务来":{"c":[9583]},"为一项":{"c":[9583]},"革作为":{"c":[9583]},"定本":{"c":[9583]},"作为一":{"c":[9583]},"省战":{"c":[9583]},"于深化":{"c":[9583]},"革的实":{"c":[9583]},"要意义":{"c":[9583]},"项重要":{"c":[9583]},"高校创":{"c":[9583]},"制定本实施方案":{"c":[9583]},"要紧":{"c":[9583]},"务院办":{"c":[9583]},"改革的":{"c":[9583]},"科教":{"c":[9583]},"革作":{"c":[9583]},"制定本":{"c":[9583]},"公厅关":{"c":[9583]},"施意":{"c":[9583]},"实施方":{"c":[9583]},"的实施":{"c":[9583]},"来抓":{"c":[9583]},"把创":{"c":[9583]},"结合我省实际":{"c":[9583]},"才强":{"c":[9583]},"教与人":{"c":[9583]},"制定":{"c":[9583]},"教与":{"c":[9583]},"合我省":{"c":[9583]},"施科":{"c":[9583]},"厅关于":{"c":[9583]},"略和":{"c":[9583]},"定本实":{"c":[9583]},"要意":{"c":[9583]},"结合我":{"c":[9583]},"是实":{"c":[9583]},"结合":{"c":[9583]},"化高校":{"c":[9583]},"意见":{"c":[9583]},"办公厅":{"c":[9583]},"施意见":{"c":[9583]},"本实":{"c":[9583]},"意义":{"c":[9583]},"重要意义":{"c":[9583]},"迫任":{"c":[9583]},"关于深":{"c":[9583]},"实际":{"c":[9583,10147]},"革的":{"c":[9583]},"院办公":{"c":[9583]},"省实":{"c":[9583]},"实施意":{"c":[9583]},"我省":{"c":[9583]},"深化高校创新创业教育改革":{"c":[9583]},"要求":{"c":[9583,10147],"m":[10147]},"与人才":{"c":[9583]},"人才强":{"c":[9583]},"科教与":{"c":[9583]},"务来抓":{"c":[9583]},"紧迫":{"c":[9583]},"把创新":{"c":[9583]},"省实际":{"c":[9583]},"实施科":{"c":[9583]},"的实":{"c":[9583]},"一项":{"c":[9583]},"重要意":{"c":[9583]},"施方":{"c":[9583]},"施方案":{"c":[9583]},"要紧迫":{"c":[9583]},"方案":{"c":[9583]},"紧迫任":{"c":[9583]},"十四届大":{"m":[10140]},"第十四":{"m":[10140],"c":[10140]},"分赛两":{"m":[10140],"c":[10140]},"初赛":{"m":[10140],"c":[10140]},"京邮电":{"m":[10140],"c":[10140]},"学第十":{"m":[10140],"c":[10140]},"子设":{"m":[10140],"c":[10140]},"子设计":{"m":[10140],"c":[10140]},"设计":{"m":[10140],"c":[10140]},"京邮电大":{"m":[10140]},"电子竞":{"m":[10140],"c":[10140]},"电大":{"m":[10140],"c":[10140]},"积分":{"m":[10140],"c":[10140]},"届大":{"m":[10140],"c":[10140]},"邮电":{"m":[10140],"c":[10140]},"列电":{"m":[10140],"c":[10140]},"段进":{"m":[10140],"c":[10140]},"分赛":{"m":[10140],"c":[10140]},"十四届":{"m":[10140],"c":[10140]},"届大学生":{"m":[10140]},"邮电大学":{"m":[10140]},"学第":{"m":[10140],"c":[10140]},"进行":{"m":[10140],"c":[10140]},"赛和":{"m":[10140],"c":[10140]},"竞赛":{"m":[10140],"c":[10140]},"邮电大":{"m":[10140],"c":[10140]},"电大学第":{"m":[10140]},"届大学":{"m":[10140],"c":[10140]},"阶段":{"m":[10140],"c":[10140]},"电子设":{"m":[10140],"c":[10140]},"计竞":{"m":[10140],"c":[10140]},"分初":{"m":[10140],"c":[10140]},"赛积":{"m":[10140],"c":[10140]},"四届":{"m":[10140],"c":[10140]},"计竞赛":{"m":[10140],"c":[10140]},"大学第十":{"m":[10140]},"第十四届":{"m":[10140]},"第十":{"m":[10140],"c":[10140]},"大学生":{"m":[10140],"c":[10140,10147]},"赛分初":{"m":[10140],"c":[10140]},"京邮":{"m":[10140],"c":[10140]},"电子":{"m":[10140],"c":[10140]},"赛两":{"m":[10140],"c":[10140]},"学第十四":{"m":[10140]},"竞赛积":{"m":[10140],"c":[10140]},"和系列":{"m":[10140],"c":[10140]},"赛积分":{"m":[10140],"c":[10140]},"学生电子":{"m":[10140]},"积分赛":{"m":[10140],"c":[10140]},"赛两阶":{"m":[10140],"c":[10140]},"分初赛":{"m":[10140],"c":[10140]},"学生电":{"m":[10140],"c":[10140]},"四届大":{"m":[10140],"c":[10140]},"初赛和":{"m":[10140],"c":[10140]},"和系":{"m":[10140],"c":[10140]},"南京":{"m":[10140],"c":[10140]},"大学":{"m":[10140],"c":[10140,10147]},"赛分":{"m":[10140],"c":[10140]},"四届大学":{"m":[10140]},"设计竞":{"m":[10140],"c":[10140]},"生电":{"m":[10140],"c":[10140]},"子竞赛":{"m":[10140],"c":[10140]},"两阶":{"m":[10140],"c":[10140]},"赛和系":{"m":[10140],"c":[10140]},"列电子":{"m":[10140],"c":[10140]},"阶段进":{"m":[10140],"c":[10140]},"大学生电":{"m":[10140]},"子竞":{"m":[10140],"c":[10140]},"竞赛分":{"m":[10140],"c":[10140]},"段进行":{"m":[10140],"c":[10140]},"南京邮电":{"m":[10140]},"两阶段":{"m":[10140],"c":[10140]},"十四":{"m":[10140],"c":[10140]},"系列":{"m":[10140],"c":[10140]},"学生":{"m":[10140],"c":[10140,10147]},"大学第":{"m":[10140],"c":[10140]},"南京邮":{"m":[10140],"c":[10140]},"电大学":{"m":[10140],"c":[10140]},"生电子":{"m":[10140],"c":[10140]},"系列电":{"m":[10140],"c":[10140]},"象为":{"c":[10140]},"院汇":{"c":[10140]},"名信息":{"c":[10140]},"方式进":{"c":[10140]},"年级":{"c":[10140]},"请各学":{"c":[10140]},"经培训":{"c":[10140]},"报名":{"c":[10140]},"手经":{"c":[10140]},"初赛将":{"c":[10140]},"考核的":{"c":[10140]},"的方式":{"c":[10140]},"继竞赛":{"c":[10140]},"各学":{"c":[10140]},"核的":{"c":[10140]},"为各":{"c":[10140]},"报名信":{"c":[10140]},"初赛将分":{"c":[10140]},"采用":{"c":[10140]},"采用操":{"c":[10140]},"对象":{"c":[10140]},"年级学生":{"c":[10140]},"运放":{"c":[10140]},"的方":{"c":[10140]},"优秀":{"c":[10140]},"拔出优":{"c":[10140]},"出优":{"c":[10140]},"选手经":{"c":[10140]},"对象为":{"c":[10140]},"机应":{"c":[10140]},"用操":{"c":[10140]},"学院":{"c":[10140]},"各专":{"c":[10140]},"级学生":{"c":[10140]},"将分":{"c":[10140]},"单片机":{"c":[10140]},"经培":{"c":[10140]},"各学院":{"c":[10140]},"赛将":{"c":[10140]},"总报名":{"c":[10140]},"赛将分":{"c":[10140]},"名对":{"c":[10140]},"2016":{"c":[10140]},"汇总":{"c":[10140]},"个方":{"c":[10140]},"运放应用":{"c":[10140]},"单片机应用":{"c":[10140]},"应用":{"c":[10140]},"选拔":{"c":[10140]},"手经培":{"c":[10140]},"报名对象为各专业":{"c":[10140]},"2017":{"c":[10140]},"级学":{"c":[10140]},"作考":{"c":[10140]},"单片":{"c":[10140]},"培训":{"c":[10140]},"式进行":{"c":[10140]},"秀的选":{"c":[10140]},"名对象":{"c":[10140]},"个方向":{"c":[10140]},"方式":{"c":[10140]},"参加后":{"c":[10140]},"机应用":{"c":[10140]},"采用操作考核的方式进行":{"c":[10140]},"式进":{"c":[10140]},"操作考":{"c":[10140]},"出优秀":{"c":[10140]},"继竞":{"c":[10140]},"总报":{"c":[10140]},"训后":{"c":[10140]},"专业":{"c":[10140,10147]},"年级学":{"c":[10140]},"训后参":{"c":[10140]},"核的方":{"c":[10140]},"息后":{"c":[10140]},"2018":{"c":[10140]},"用操作":{"c":[10140]},"拔出":{"c":[10140]},"放应用":{"c":[10140]},"院汇总":{"c":[10140]},"作考核":{"c":[10140]},"后参":{"c":[10140]},"操作":{"c":[10140]},"为各专":{"c":[10140]},"信息":{"c":[10140]},"后继竞":{"c":[10140]},"学院汇":{"c":[10140]},"的选手":{"c":[10140]},"各专业":{"c":[10140]},"加后继":{"c":[10140]},"放应":{"c":[10140]},"后继":{"c":[10140]},"加后":{"c":[10140]},"参加":{"c":[10140]},"后参加":{"c":[10140]},"请各学院汇总报名信息后":{"c":[10140]},"象为各":{"c":[10140]},"培训后":{"c":[10140]},"选手":{"c":[10140]},"的选":{"c":[10140]},"请各":{"c":[10140]},"秀的":{"c":[10140]},"考核":{"c":[10140]},"名信":{"c":[10140]},"优秀的":{"c":[10140]},"片机应":{"c":[10140]},"方向":{"c":[10140]},"汇总报":{"c":[10140]},"选拔出":{"c":[10140]},"运放应":{"c":[10140]},"报名对":{"c":[10140]},"片机":{"c":[10140]},"为了深":{"m":[10147],"c":[10147]},"以能力和职业发展为导向":{"m":[10147],"c":[10147]},"业发展":{"m":[10147],"c":[10147]},"营销":{"m":[10147],"c":[10147]},"展为导向":{"m":[10147]},"践教":{"m":[10147],"c":[10147]},"才培养要":{"m":[10147]},"为了深化":{"m":[10147]},"为导向":{"m":[10147],"c":[10147]},"职业发展":{"m":[10147]},"化教育部":{"m":[10147]},"和职业":{"m":[10147],"c":[10147]},"实践":{"m":[10147],"c":[10147]},"了深":{"m":[10147],"c":[10147]},"育部":{"m":[10147],"c":[10147]},"育与":{"m":[10147],"c":[10147]},"发展为导":{"m":[10147]},"养要":{"m":[10147],"c":[10147]},"发展为":{"m":[10147],"c":[10147]},"能力和职":{"m":[10147]},"力和":{"m":[10147],"c":[10147]},"为导":{"m":[10147],"c":[10147]},"以能力":{"m":[10147],"c":[10147]},"以能":{"m":[10147],"c":[10147]},"和职":{"m":[10147],"c":[10147]},"的人才培养要求":{"m":[10147],"c":[10147]},"展为导":{"m":[10147],"c":[10147]},"化教育":{"m":[10147],"c":[10147]},"职业":{"m":[10147],"c":[10147]},"了深化":{"m":[10147],"c":[10147]},"与营":{"m":[10147],"c":[10147]},"展为":{"m":[10147],"c":[10147]},"立创新":{"m":[10147],"c":[10147]},"力和职":{"m":[10147],"c":[10147]},"的人才培":{"m":[10147]},"销实":{"m":[10147],"c":[10147]},"深化教":{"m":[10147],"c":[10147]},"以能力和":{"m":[10147]},"教学":{"m":[10147],"c":[10147]},"业发展为":{"m":[10147]},"导向":{"m":[10147],"c":[10147]},"建立创新创业教育与营销实践教学":{"m":[10147],"c":[10147]},"为了":{"m":[10147],"c":[10147]},"培养要求":{"m":[10147]},"深化教育":{"m":[10147]},"立创":{"m":[10147],"c":[10147]},"建立":{"m":[10147],"c":[10147]},"的人":{"m":[10147],"c":[10147]},"建立创":{"m":[10147],"c":[10147]},"职业发":{"m":[10147],"c":[10147]},"和职业发":{"m":[10147]},"业发":{"m":[10147],"c":[10147]},"教育部":{"m":[10147],"c":[10147]},"力和职业":{"m":[10147]},"培养要":{"m":[10147],"c":[10147]},"能力":{"m":[10147],"c":[10147]},"养要求":{"m":[10147],"c":[10147]},"能力和":{"m":[10147],"c":[10147]},"的人才":{"m":[10147],"c":[10147]},"化教":{"m":[10147],"c":[10147]},"为了深化教育部":{"m":[10147],"c":[10147]},"了深化教":{"m":[10147]},"促学":{"c":[10147]},"动高等":{"c":[10147]},"查分":{"c":[10147]},"等院":{"c":[10147]},"业课程":{"c":[10147]},"学的机":{"c":[10147]},"习兴":{"c":[10147]},"营销实":{"c":[10147]},"系和":{"c":[10147]},"在校":{"c":[10147]},"激发学生理论联系实际的积极性":{"c":[10147]},"的改":{"c":[10147]},"极性":{"c":[10147]},"内容的":{"c":[10147]},"的积":{"c":[10147]},"实践课":{"c":[10147]},"等院校":{"c":[10147]},"发学生":{"c":[10147]},"生对":{"c":[10147]},"的改革":{"c":[10147]},"论联":{"c":[10147]},"养在":{"c":[10147]},"论联系":{"c":[10147]},"积极性":{"c":[10147]},"生理":{"c":[10147]},"践课":{"c":[10147]},"实践教":{"c":[10147]},"践教学":{"c":[10147]},"以赛":{"c":[10147]},"对市场":{"c":[10147]},"市场":{"c":[10147]},"的学":{"c":[10147]},"学生对":{"c":[10147]},"发学":{"c":[10147]},"系实":{"c":[10147]},"的机":{"c":[10147]},"和内容":{"c":[10147]},"培养在":{"c":[10147]},"理论联":{"c":[10147]},"的学习":{"c":[10147]},"院校":{"c":[10147]},"和内":{"c":[10147]},"践课程":{"c":[10147]},"课程的":{"c":[10147]},"对市":{"c":[10147]},"的积极":{"c":[10147]},"内容":{"c":[10147]},"析专业":{"c":[10147]},"生对市":{"c":[10147]},"学习":{"c":[10147]},"赛促学":{"c":[10147]},"联系":{"c":[10147]},"兴趣":{"c":[10147]},"分析":{"c":[10147]},"以赛促":{"c":[10147]},"联系实":{"c":[10147]},"课程体":{"c":[10147]},"激发":{"c":[10147]},"积极":{"c":[10147]},"赛促":{"c":[10147]},"程的学":{"c":[10147]},"体系":{"c":[10147]},"容的":{"c":[10147]},"激发学":{"c":[10147]},"推动高":{"c":[10147]},"际的积":{"c":[10147]},"教育与":{"c":[10147]},"容的改":{"c":[10147]},"销实践":{"c":[10147]},"实际的":{"c":[10147]},"校大学":{"c":[10147]},"生理论":{"c":[10147]},"院校创":{"c":[10147]},"分析专":{"c":[10147]},"高等院":{"c":[10147]},"程体系":{"c":[10147]},"理论":{"c":[10147]},"育与营":{"c":[10147]},"程体":{"c":[10147]},"体系和":{"c":[10147]},"市场调":{"c":[10147]},"业课":{"c":[10147]},"调查分":{"c":[10147]},"的机制":{"c":[10147]},"在校大":{"c":[10147]},"专业课":{"c":[10147]},"与营销":{"c":[10147]},"系和内":{"c":[10147]},"校大":{"c":[10147]},"程的":{"c":[10147]},"以赛促学的机制":{"c":[10147]},"学习兴":{"c":[10147]},"促学的":{"c":[10147]},"查分析":{"c":[10147]},"系实际":{"c":[10147]},"学生理":{"c":[10147]},"场调":{"c":[10147]},"养在校":{"c":[10147]},"课程":{"c":[10147]},"析专":{"c":[10147]},"调查":{"c":[10147]},"学的":{"c":[10147]},"际的":{"c":[10147]},"动高":{"c":[10147]},"场调查":{"c":[10147]}},"scope":{"index_id":"cxcy__exam__2018","source_id":"cxcy","facet":"exam","year":"2018","shard_ids":["cxcy__exam__detail__2018__首页__b0","cxcy__exam__detail__2018__首页__b2","cxcy__exam__detail__2018__首页__b3"]}}